doWellSecureGithubRepository/__init__.py
doWellSecureGithubRepository/doWellSecureGithubRepository.py
DoWell_Secure_Github_Repository-1.0.0.dist-info/METADATA
DoWell_Secure_Github_Repository-1.0.0.dist-info/WHEEL
DoWell_Secure_Github_Repository-1.0.0.dist-info/top_level.txt
DoWell_Secure_Github_Repository-1.0.0.dist-info/RECORD
