Metadata-Version: 2.1
Name: DoWell-Secure-Github-Repository
Version: 1.0.0
Summary: Dowell secure github repository from DoWell
Author: DoWell UX Living Lab
License: Apache License 2.0
Requires-Dist: requests
